odoo10_addon_web_ckeditor4-10.0.1.0.0.99.dev3-py2.7-nspkg.pth
odoo/addons/web_ckeditor4/README.rst
odoo/addons/web_ckeditor4/__init__.py
odoo/addons/web_ckeditor4/__manifest__.py
odoo/addons/web_ckeditor4/i18n/web_ckeditor4.pot
odoo/addons/web_ckeditor4/models/__init__.py
odoo/addons/web_ckeditor4/models/ckeditor_monkeypatch.py
odoo/addons/web_ckeditor4/static/description/icon.png
odoo/addons/web_ckeditor4/static/lib/ckeditor/CHANGES.md
odoo/addons/web_ckeditor4/static/lib/ckeditor/LICENSE.md
odoo/addons/web_ckeditor4/static/lib/ckeditor/README.md
odoo/addons/web_ckeditor4/static/lib/ckeditor/build-config.js
odoo/addons/web_ckeditor4/static/lib/ckeditor/ckeditor.js
odoo/addons/web_ckeditor4/static/lib/ckeditor/config.js
odoo/addons/web_ckeditor4/static/lib/ckeditor/contents.css
odoo/addons/web_ckeditor4/static/lib/ckeditor/styles.js
odoo/addons/web_ckeditor4/static/lib/ckeditor/adapters/jquery.js
odoo/addons/web_ckeditor4/static/lib/ckeditor/lang/af.js
odoo/addons/web_ckeditor4/static/lib/ckeditor/lang/ar.js
odoo/addons/web_ckeditor4/static/lib/ckeditor/lang/bg.js
odoo/addons/web_ckeditor4/static/lib/ckeditor/lang/bn.js
odoo/addons/web_ckeditor4/static/lib/ckeditor/lang/bs.js
odoo/addons/web_ckeditor4/static/lib/ckeditor/lang/ca.js
odoo/addons/web_ckeditor4/static/lib/ckeditor/lang/cs.js
odoo/addons/web_ckeditor4/static/lib/ckeditor/lang/cy.js
odoo/addons/web_ckeditor4/static/lib/ckeditor/lang/da.js
odoo/addons/web_ckeditor4/static/lib/ckeditor/lang/de.js
odoo/addons/web_ckeditor4/static/lib/ckeditor/lang/el.js
odoo/addons/web_ckeditor4/static/lib/ckeditor/lang/en-au.js
odoo/addons/web_ckeditor4/static/lib/ckeditor/lang/en-ca.js
odoo/addons/web_ckeditor4/static/lib/ckeditor/lang/en-gb.js
odoo/addons/web_ckeditor4/static/lib/ckeditor/lang/en.js
odoo/addons/web_ckeditor4/static/lib/ckeditor/lang/eo.js
odoo/addons/web_ckeditor4/static/lib/ckeditor/lang/es.js
odoo/addons/web_ckeditor4/static/lib/ckeditor/lang/et.js
odoo10_addon_web_ckeditor4-10.0.1.0.0.99.dev3.dist-info/METADATA
odoo10_addon_web_ckeditor4-10.0.1.0.0.99.dev3.dist-info/RECORD
odoo10_addon_web_ckeditor4-10.0.1.0.0.99.dev3.dist-info/WHEEL
odoo10_addon_web_ckeditor4-10.0.1.0.0.99.dev3.dist-info/namespace_packages.txt
odoo10_addon_web_ckeditor4-10.0.1.0.0.99.dev3.dist-info/top_level.txt
